{
  "doc_id": "doc_20260206_105844_b5f457fa",
  "page": 1,
  "text": " \n \n \n \n \nاللجنة التقنية للكورونا بالحمل \n وزارة الصحة–\n لبنان \n  \n \n \n \n \n المبادىء التوجيهية للعيادات الخارجية لحاالت\nكوفيد-\n91\n \n \nنيسان ،\n0202\n \nتم إعداد هذا الكتيب من قبل اللجنة التقنية للكورونا والحمل - لبنان كجزء من \n سلسلة \n المبادئ التوجيهية للعيادات الخارجية لحاالت الكوفيد-\n91\n للسيدات الحوامل.\n \nبالتعاون مع \n \n \n \n \n \n",
  "lines": [],
  "blocks": [],
  "entities": [],
  "image_path": "data\\images\\doc_20260206_105844_b5f457fa\\raw\\page_0001.png",
  "preprocessed_image_path": "data\\images\\doc_20260206_105844_b5f457fa\\preprocessed\\page_0001.png",
  "ocr_fallback": true
}